kubeleds/__init__.py
kubeleds/app.py
kubeleds/constants.py
kubeleds/utils.py
kubeleds/commands/__init__.py
kubeleds/commands/cluster.py
kubeleds/commands/init.py
kubeleds/commands/led.py
kubeleds/commands/pod.py
kubeleds/commands/show.py
kubeleds-0.0.1.dist-info/LICENSE
kubeleds-0.0.1.dist-info/METADATA
kubeleds-0.0.1.dist-info/WHEEL
kubeleds-0.0.1.dist-info/entry_points.txt
kubeleds-0.0.1.dist-info/top_level.txt
kubeleds-0.0.1.dist-info/RECORD
