Metadata-Version: 2.1
Name: kubeleds
Version: 0.0.1
Summary: monitor kubernetes clusters using adafruit neopixels
Home-page: UNKNOWN
Author: Robert Evans
License: UNKNOWN
Platform: UNKNOWN
Classifier: Programming Language :: Python :: 3.6
Classifier: Programming Language :: Python :: 3.7
Classifier: Programming Language :: Python :: 3.8
Classifier: Operating System :: OS Independent
Classifier: Development Status :: 4 - Beta
Requires-Dist: RPI.GPIO
Requires-Dist: adafruit-blinka
Requires-Dist: adafruit-ws2801
Requires-Dist: click
Requires-Dist: kubernetes
Requires-Dist: requests
Requires-Dist: rich (<=7.1.0)
Requires-Dist: simple-term-menu
